hello_flit/__init__.py
hello_flit/main.py
sedgwickz_hello_flit-0.5.dist-info/WHEEL
sedgwickz_hello_flit-0.5.dist-info/METADATA
sedgwickz_hello_flit-0.5.dist-info/RECORD
