Metadata-Version: 2.1
Name: sedgwickz_hello_flit
Version: 0.5
Summary: My first flit package 
Author: sedgwickz
Author-email: kunnsh@gmail.com
Classifier: License :: OSI Approved :: MIT License
